{
  "id": "00242dfc-a91d-4b47-997d-0bb9d97f587a_1",
  "content": "분야에를 가주간다고요. 요서 3대축이 이루어지는 겁니다. 어. 그렇게 되는데. 요래서 인자 요기 인자 현상이 어떡해가주구 이런 일이 벌어지 고 있느냐면, 요기 3:7로 해갖고 70프로 우리가 성장할 때까지, 이때까지는 경제를 창출해 내고 이 서로가 전부 다 챙겨가고 이런 일이 일어나요. 이런 일이 일어나는데 문제는 기업 이 담당해줘야 될 게 있고. 어, 경제를 가주가는 쪽은 분명히 담당해줘야 될 게 있어요. 기 업이 담당해줘야 될 게 있고. 또 정부가 담당해줘야 될 게 있고. 또 종교가 담당해줘야 될 게 있어요. 어. 종교조직이 담당을 이 사회에 잘못되지 않도록 담당해줘야 될 것들이 있다 라는 거죠. 음. 칸데. 정부는 이 세금을 걷어가서 자기가 하는 담당을 해냅니다. 에, 감당해 내요. 하고 자기가 할 일을 찾아서 자꾸 해요. 하는데. 기업은 자기가 이 경제는 챙겨가면서 이 사회가 지금 앞으로 바르게 이렇게 저 틀리게 안 되도록 이런 담당할 일을 몬 했어요. 몬 하고 가고 있는 겁니다, 지금. 종교도 자기가 할 일을 담당을 몬 하고 가고 있는 거예요. 요걸 세 군데서 자기가 해야 될 담당을 했더라면 이 사회는 절대 어렵게 안 됩니다. 한데 이게서 두 군데서 지금 자기가 해야 될 게 뭔지를 모르고 돈만 챙기고 있어요. 요래 되면 어떻게 되냐? 종교가 부자 되지요. 기업 부자 됩니다. 경제인들 부자 돼요. 아, 왜? 돈 챙겨 가주고 자기들이 해야 될 거는 안하고 이걸 챙기기만 하니까 이건 자꾸 쌓이죠. 그래서 종 교가 지금 그만한 경제를 가주고 있는 이유가 그걸 자꾸 쌓아가 가주고 있기 때문이에요. 할 일은",
  "metadata": {
    "source": "",
    "filename": "",
    "label": "",
    "chunk_index": 1
  }
}