{
  "id": "0221cfe6-4507-4c4a-a8a8-b53b1a1bce01_0",
  "content": "제목: [정법 시사/이슈] 402강 박찬호, 문대성의 성공미래-2 언어: ko 그게 이제 내가 이제 뭐 소속사도 해 가지고 난중에 뭐 내가 필요한 사람들이 이쪽에 좋은 일을 좀 하시라 그러면 전부 다 이게 협조 다 해요 이래서 나는 앞으로 총재가 될 수 있는 대표로 지금 해 갖고이 총재가 될 수 있는 그런 기반을 만들어 가면서 국제 사회에 보람 있고 떠 있는 일을 하는 이런 식으로 해 갖고 내가 그쪽으로 이제 나가는 거죠 나가면 나 그거 나가다 보면 그쪽에 못 사는데 보면은 뭐 이렇게 야구도 어린아이들은 야구도 하고 싶고 그럼 그쪽에 내가 시범 저거하면 학교도 좀 애나 열어 가지고 이런 애들도 할 수 있게도 만들어 주고 응 그러면서 이런 것들이 국제적으로 뭔가를 이렇게 그 메시지가 되게끔 이런 거 프로그램을 짤 수도 있고 그뭐 어떤 나라 이제 후진국에 가니까 후진국에 출시하려고 야구 하려 그러잖아요 그런데다가 어 그 내가 가서 시범 야구 같은 것도 이렇게 하면서 이 힘을 만들어 줄 수도 있고 여러 가지 이제 그 자기 이제 제주 가지고 크게 이제 국제 사회에 어 뭔가를 메시지를 줄 수 있는 이러한 그이 재단을 하나 이렇게 저 그만해도 재단을 하나 설립을 해 놓으면 이거 가지고 그는 국제 사업을 하는 거죠 그러면 총재로 변해요 근데 렇게 하면 링크를 어디로도 걸 수 있고 뭐 국제적인 이런 그 클럽 그 저 이제 저 저거 기구에가 전부다 그 이런 걸 걸 수도 있단 말이죠 그런 프로젝트를 하나씩 만들어서 그런 사업을 하고 이렇게 하면은 그 우리가 국제적으로 그 CF 그런 거 적이 되잖아요 이게 커팅이 되잖아요 뭐가 어",
  "metadata": {
    "source": "",
    "filename": "",
    "label": "",
    "chunk_index": 0
  }
}