{
  "id": "43afd197-81d6-4fa7-9db4-5160ed3c14f1_1",
  "content": "나의 발전 할 수 있는 이러한 비용이 전부 다 그 잔고로 묶어버리니까 내 발전을 몬 합니다. 어, 오늘 내 발전을 몬 하면 어떻게 되냐면 아, 내가 이 소고기도 한 그 한 달에 한 두번은 먹어야 된다. 예를 들어서. 영양에 필요있다라는 거죠. 어, 그러고 책도 한 두권 봐야 돼요. 아. 또 저쪽에 그 여 바람 씌러도 한 두번 가야 됩니다. 어? 어. 가야 되고. 내가 쪼끔 수준이 쪼 끔 있다면 수준이 쪼끔 있다면, 뭐 보통 요새는 고등교육을 받아서 직장생활을 하니까 이런 사람이라면 한 달에 한번 정도 안 그러면 석 달에 한번 정도는 저쪽에 오페라, 오펠라도 한 번 봐야 돼요. 어? 그런 것도. 연극 같은 것도 함 보고. 미술관에도 한번 가서 어, 이렇게 둘러 보고. 이런 거는 항상 내 마인드 때문에 그런 거를 해야만 됩니다. 음. 여 만일에 그런 거를 안했다. 그죠? 안하고 이걸 비축량으로 모아가지고 돈이 자꾸 모인다. 모이면 어떻게 되냐면, 너가 이 돈이 모이갖고 니한테 도움이 될 거 같지만 사회에 뒤떨어져요. 사회에 뒤 떨어져갖고 분별력이 떨어져. 음. 그래서 이 돈이 쪼끔 어느 정도 모이게 되면 이걸 갖고 뭔가를 욕심을 내서 뭔가를 더 해가주고 인자 쪼끔 모이니까 내가 뭔가를 해가주구 이거로 나도 독립할라꼬 든단 말이죠. 독립을 할려고 들면 니 마인드가 약하면 나가면 정확하게 사 기 당하고 악어가 입을 딱 벌리고 있는 세상에 나와가주고 너는 절대로 이거로 성공 몬 하 고 망합니다. 이런 일이 벌어진다라는 얘기죠. 어? 우리도 쪼매나게 뭐 하자고 이래가 나가 가주고 홀딱 띠이가주고 인생은 인생대로 망신당",
  "metadata": {
    "source": "",
    "filename": "",
    "label": "",
    "chunk_index": 1
  }
}