{
  "id": "6042676f-743c-455b-9d7e-afb160b0e175_2",
  "content": "는 겁니다. 아픈 사람한테 문병을 가는 사람은 너는 공부해야 돼. 만일에 공부안하고 그냥 갖다 와서 “아이고 빨리 일나라.” 뭐 이러고 그냥 뭐 이렇게 가다 가 나왔다? 어 맻 번 그런 일이 또 딴 데도 문병을 가는 공부를 합니다. 문병을 가는 놈이 가지, 안 가거든요. 문상을 가는 것도 가는 사람이 가지, 안 가. 한데 그게 갔다 왔다 하면 서 지금 니 공부가 크게 걸렸다라는 사실이거든요. 그럼 병원에 이렇게 자꾸 다니는 사람은 병원 가서 병원 다니면서 이렇게 뭐가 공부가 걸렸는데 이걸 몬하면 니가 병원에 눕습니다. 음. 그러고 저 이게 봉사활동 다닌다고 이렇게 해갖고 쩌 다니는 사람은 그기에 다니면서 지금 공부를 시키고 있는 것인데 넘 도우러 간다고 지금 착각을 하고 있어요. 시간 지나면 니가 봉사 수급자가 돼요. 음. 이걸 도왔다라는 생각을 한다는 얘기죠. 어렵게 사는 사람한 테 내가 갈려면 니가 물질을 쪼끔 들고 가야 되는 겁니다. 몸이 성한 사람이 몸이 어려운 사람한테 내가 갈려면 내 몸을 가주고 쫌 딲아주든지 안아주든지 이런 걸 쫌 해줘야만 갈 수 있는 자격을 갖게 되는 것이지. 이걸 내가 내 돈이 쫌 있다고 저 도왔다라고 생각을 한 다는 얘기죠. 너는 쪼꼼 있으면 니 가족 중에 봉사수급자가 되든지 니가 그래 되든지 니가 어려움이 처해갖고 넘 도움이 필요해지든지, 이런 것들 줄이 지금 들어와 있기 때문에 그 공부를 시키는 거거든요. 가까이 왔다는 거죠. 어. 멀리 있다라는 것은 책을 본다든지 누구 한테 이야기만 듣습니다. 내한테 이런 기회가 올 수 있는 기 멀리 있다면. 시간이 아직 더 걸릴 꺼라면",
  "metadata": {
    "source": "",
    "filename": "",
    "label": "",
    "chunk_index": 2
  }
}