{
  "id": "79deee22-c41e-459e-9911-2275495aabc1_2",
  "content": "없는일 이런 힘이 나한테 온다면 크게 뜻 있고 보람 있는 일을 백성들이 못하는 걸 전부다 내가 해내야 될 준비도 해야 됩니다 그렇게 할 수 있는 내 자격을 안 갖췄다면 지금부터 돈도 들어오대 공부도 하십시오 이래 가지고 사람을 일으켜 내야 된다라는 얘기죠 근 내가 이동 수를 잘못 알고 이동을 했고 그런 데서 안 좋은 것들을 많이 겪다가 보니까 이것이 남들은 이해가 안 되고 닥친 사람은 내가 경험을 해 버렸고 이런 이제 일들이 있다 보니까 아직까지 전 뭐다이 혼선이 오고 있는 거예요 이런 법칙을 정확하게 내가 이제 아르게 줌으로 이것은 과거에 있었던 일들입니다 앞으로 미래는 어떻게 되느냐 어디에든지 가고 싶은 대로 가십시오 내가 마음 끌리는 대로 하고 싶은 데로 인자는 마음껏 할 수 있는 세상이 열립니다 2013년도부터 미래가 열리지만 지금은 가족이기 때문에 지금또 운용이 됩니다 그래서 우리는 어떠한 곳에 집착에 달리지 마라 치우치지 마라 내가 망끝 이제 운용하는 시대 이제 인본 시대가 돌아오나 사람이 운용하는 시대라는 이야기입니다 이때까지는 신들이 우리를 이끌었고 영혼들이 이끌었고 우리는이 사주를 가지고 이끄는 대로 우리는 갔어야 됐던 시대를 이때까지 살았다 미래는 2013년도부터는 신이 이끌어 주지 않는다 이제 장점과 단점이 있죠 제 이게 부모님이 자식을 키울 때 무식 어릴 이럴 때는 손을 잡고 여기다 데고 가고 여기에서 있으라 그럽니다 그리고 갈 때 되면 같이 가자 하면 따라가야 돼요 왜 우리가 힘이 없거든요 그래서 부모가 손을 잡고 이끌어 주던 시대가 있었고 이것이 이때까지 우리가 살아왔던 우리 인간의",
  "metadata": {
    "source": "",
    "filename": "",
    "label": "",
    "chunk_index": 2
  }
}