{
  "id": "822049d5-1d1f-4d68-b480-c25665e8b12d_17",
  "content": "가 있는거야. 답이 없었어. 이걸 풀어내는 거예요. 얼마나 중요한 공부 냐? 이제는 도술의 시대를 마감하고 법의 시대를 만드는 것이다. 법은 무엇을 뜻하냐? 바른 가르 침을 뜻한다 바르게 가르치니 몰라서 했든. 그래서 누구도 이 지상에서 풀어주지 못하는 것들을 바른 공부를 하고 바르게 깨우치려고 노력을 하고 바르게 살려고 노력을 하니. 이제는 모두 다시 돌려 줄 수 있어진다 이 말이야. 여기에 오신 분들은 젊은 분들은 놔 놓고 그래서 내가 젊은 사 람들을 좋아하는 거요. 아직까지 매를 다 안쳐 가지고 왔으니까. 우리 선배님들은 반성을 해야 한다. 안하면 내가 안 풀어 준다. 나는 그 힘을 가지고 온 사람이고 다 성불을 받아 본 사람들이 고. 한데 언젠가부터 꽉 막혀 가지고 가슴에 아주 피멍이 들었어. 이것을 풀리지 않고 15년 20년 다시 몸이 아프던 가족이 어렵던 전부 다 의가 상했던 다들 전부 어려워 졌는데. 이것이 지금 여 기에 가도 안 되고 저기에 가도 안 되고 아무리 헤매도 안 되고 침을 갖다 하루에 3집을 다니면 서 쑤셔도 안 되고 그랬던 것이 여기에서 내가 침을 쑤셨나, 부적을 써서 긁어 주었나, 돼지 대 가리를 올려 줘서 뭐 어떻게 재를 올려 주었나. 응. 뭐 하느님 안 믿는다고 내가 뭐 혼을 내기를 했나. 우리 삶을 잘못산 것을 이유를 가르쳤지 가르치니 그게 이해가 가서 공부를 하고 바르게 살려고 노력을 하니까 내가 기를 가지고 이렇게 쑤셔가 넣기를 했나 안 해도 다 풀려 버렸다 다 낫어 버렸고 풀려 버렸다. 이게 무엇을 뜻하냐. 법의 힘은 눈에 보이지 않는다. 공치사도 하지 않으며, 색깔도",
  "metadata": {
    "source": "",
    "filename": "",
    "label": "",
    "chunk_index": 17
  }
}