{
  "id": "9febf758-f9d4-420b-8631-361aee1d8ae6_22",
  "content": "게 쓰면 인류를 이끄는 지도자들이 될 것이요. 이 천기를 쓰지 못하면 평민이나 똑같습니다. 100V 전자제품. 우리가 전자제품 이거는 100V인데 백 볼트, 우리는 1000V를 쓸 수 있는 마음의 에너지를 가지고 있는데 이것이 천기를 쓰는 천손들입니다. 마지막까지 다 온 사람들입니다. 하니 께 이것을 우리가 못쓰게 되면 100V 전자제품이랑 똑같습니다. 100V는 어데다 쓰느냐. 사적으로 쓸 때 쓰이는 것이고, 사적으로. 개인적으로 살기 위해서 쓰는 것. 사도, 사 생각. 나의 생각. 내 방법. 이런 것들이고. 그거는 물질로 살 때만 이야기하는 것입니다. 천기는 언제 쓰이느냐. 공적으 로 니 생을 살 때. 공적인, 공적인 일을 할 때. 공적으로 살고, 타인을 위해서 살고 타를 위해서 살고, 니를 위해서 사는 것이 아닐 때. 이때 천기가 거게서 작동을 합니다. 우리는 프리볼트로 걸 려가 있는 것입니다. 근데 우리가 못쓰는 것이죠. 그래서 고때 지혜라는 게 발생해서 나옵니다. 나오면 세상에 못할 일이 없고, 내가 말하는대로 이루어지고 대자연은 스스로 너와 함께 할 것이 고 이렇게 프리볼트로 연결 해가꼬 우리가 그 기운을 쓰면 이 민족이 인류를 구원하고, 인류를 이 끄는 민족이 될 것이고, 이것을 못하게 되면 우리는 인류를 이끈다라는 소리는 말짱 새빨간 소리 입니다. 하니까 그래서 이 민족을 두고 관음 민족이라. 관음. 이 민족이 원래가 관음입니다. 관, 관세음. 응? 어, 그렁께 보살이라는 하는 것은 보행. 어, 이렇게 남을 위해서 행하는 것을 이야기 하는 것이고 그래서 이 준말이 인자 관음이라고 이야기하는 것이",
  "metadata": {
    "source": "",
    "filename": "",
    "label": "",
    "chunk_index": 22
  }
}