{
  "id": "a838d259-f651-42e1-9ba2-efa26fe8d46b_2",
  "content": "헌데 우 리가 그 아 그 뭐 뭐 몇 십 년 전만 해도 우리가 전부 다 무식할 때지요. 집안이 다 무식했 고, 전부 다 무식한 데서 우리는 요 씨를 골라갖고 지금 지식을 갖춧고 뭐하고 이렇게 하고 있는 중이었었고. 그래가주고 보수 집안에는 경제를 갖췄고. 어. 진보 집안에는 지식을 아주 인제 이 색다른 지식을 갖춧고. 어. 노동자는 열심히 고생했고. 그래갖고 지금 우리는 어떻 게 살고 있고. 요게 딱 정해져가 있단 말이죠. 어. 한데 여기다 돌 떤지면 안 돼요. 지금 바 르게 되가 있는 거야. 어. 한데 이 기운이 움직이게 하는 방법이 이 진보지식인이 어뜬 설 계를 해갖고 세상에 내놓느냐 따라서 이 경제가 움직여서 회전이 돼요. 이걸 몬 해내면 지 식을 다 갖췄다라고 이야기 하면 안 되고. 지식을 갖췄어도 아직까지 내가 깨달질 못했다라 고 생각을 하고. 이런 거를 바르게 운용할지 모르면 이러면 세상의 이 주인공이 안 되죠. 에? 부모들이 원하는 지식을 다 갖춘 사람이 아니라는 거죠. 어. 요런 거. 지금 지식인들이 굉장히 중요할 땝니다. 당신들 운명이 걸려가 있어. 어. 한데 이 운명이 이 나라 운명이 걸 려가 있거든. 이 나라 운명이 인류의 운명이 걸려가 있다고, 지금. 굉장히 중요할 때예요. 이게 지금. 지식인, 우리가 지금 쪼꼼 백성들이 아파도 지식인들이 가닥이 잡히게끔 해줘야 되는 것이 우리가 지금, 우리가 고생핸 거를 마무리해가 진짜 잘 풀기 위해서 노력을 해야 되는 일이거든요. 음. 그래서 지금 인자 학생들, 뭐 학생들 카다보니까 자꾸 인자 글루 지식 쪽으로 가는데. 학생들은 어 그렇게 해갖고 어 우",
  "metadata": {
    "source": "",
    "filename": "",
    "label": "",
    "chunk_index": 2
  }
}