{
  "id": "e4c88cfb-6fd4-46f9-a11b-484d1bea8ab3_12",
  "content": "금 모르는 겁니다. 우리가 왜 정성껏 그 사람한테 아닌 거는 정성을 다 해서 그걸 아니할 수 있도록 노력을 다 해야만 되는가? 아니다라고 니가 분명히 선을 그었다면 그거 는 아니하게끔 만들어 내야 됩니다. 그걸 만드는 방법을 우리는 친구한테든, 가족한테든, 만 드는 방법을 지금 잘 우리가 못 하는 거죠. 그걸 잘 할라 하면 어떻게 해야 되냐? 지금 안 되는 방법은 “그거 하지 마라 했잔하요.” 이런다 말이야. “그거 그렇게 하면 이렇게 해가 안 되요. 그마 하지 마이소.” 이래, 이래. 맞지요? 씨게 안 웃는 거 보니 아닌가봐? 그렇게 하는데, 그렇게 하면 절대 안 듣습니다. 신용이 벌써 하지 마라 하면 안 해버리면 신용이 있는 사람이니까 그냥 괜찮은데, 그냥 들어가는데, 하지마라하는데 안 듣는 사람은 신용을 그만큼 잃은 겁니다. 내가 그러니까 그렇게 해가꼬는 절대로 그걸 안 듣습니다. 난중에는 디게 그러면, 막 자꾸 보채면 “나는 안 되면 안 되는 한이 있어도 할란다.” 이카고 합니다. 완전 똥고집으로 가버립니다. 그렁께 니가 잘못 지금 말리는 방법이 잘못됐다는 겁니다. 정 확하게 아르켜 줘요. 한데 그거는 그렇게 하면 절대 안 되고, 어떻게 해야 되냐? 안 되는 걸 알았는데 한 번 이야기를 딱 하니까 안 먹힌다. 안 먹히면, 수단과 방법을 다 써 아양을 다 떨어야 됩니다. 신용을 잃었으니까. 신용을 잃었으니까 아주 내 있는 재주를 다 부려가 꼬 아양을 다 떨어야 돼. 니가 자존심이 좀 상해도 앞에 니가 좀 저 일이 잘 안 돼가꼬 크 게 일 터져가꼬 니한테 그게 봉변이 안 들어오려면 그걸 막으려면 지금 좀",
  "metadata": {
    "source": "",
    "filename": "",
    "label": "",
    "chunk_index": 12
  }
}