{
  "id": "f3b7ad9e-87df-41b8-8f96-107c9b7ff8f9_3",
  "content": "에게 존경받는 것이 성공이다. 50. 내 앞에 있는 자가 부처다. 51 공부하는 자는 알고도 몰라야 한다. 52. 가난은 죄다. 가난한 이를 물질로만 돕지 말고 가난할 수밖에 없는 이유를 찾게 하라. 53. 돈을 잘 운용하는 자가 돈을 더 크게 움직인다. 54. 이념을 가진 자와 이념이 없는 자는 출발점이 같아도 종착점은 하늘과 땅 차이다. 55. 종교가 존재하는 이유는 천국에 가기 위함이 아니라 현재의 삶을 바르게 살기 위한 교육이 목적이어야 한다. 56. 말을 들어야 할 자리가 있고 말을 해야 할 자리가 있다. 57. 말은 내가 하는 것이지만 받아들이는 것은 상대다. 진정한 대화는 상대를 이해시키는 것이다. 58. 참된 스승은 상대의 질량에 맞는 가르침을 주는 사람이다. 59. 나의 말을 상대가 이해하지 못한다면 상대의 실력이 부족한 것이 아니라 내 실력이 부족한 것이다. 60. 화를 내는 것은 내 실력이 부족한 것임을 알아야 한다. 61. 좋은 인연을 맺으려면 상대를 존중해야 한다. 62. 경청은 관계의 시작이자 대화의 근본이다. 63. 내 육신이 이 세상을 살아가고 있지만 사실은 내 영혼이 이 세상을 살고 있는 것이다. 삶의 목적은 영혼의 성장을 위함이다. 64. 착하게 살지 마라. 착하게 산 사람이 어려워진 데에는 이유가 있다. 바른 분별로 살아간다면 삶은 절대 어려워지지 않는다. 65. 대자연의 물질 에너지가 하느님이다. 제2부 나를 찾아가는 길 66. 집착은 놓는다고 해서 놓아지는 것이 아니라 욕심으로부터 초연하면 집착은 저절로 사라진다. 67.. 바르게 배운 사람은 상대를 무시하지 않거나 절대로",
  "metadata": {
    "source": "",
    "filename": "",
    "label": "",
    "chunk_index": 3
  }
}