{
  "document_id": "advanced/012. 을동2  공도사상.rtf_chunk_0",
  "file": "012. 을동2  공도사상.rtf_chunk_0",
  "tags": {
    "윤회와 전생": 1.0,
    "수행": 1.0,
    "분노": 1.0,
    "존재와 죽음": 1.0
  },
  "metadata": {
    "filename": "012. 을동2  공도사상.rtf",
    "format": ".rtf",
    "file_path": "data/jungbub_teachings/advanced/012. 을동2  공도사상.rtf",
    "source": "천공 스승님 정법 가르침",
    "lecture_number": null,
    "title": null,
    "file_hash": "a93b86ac76792d8046bb7b45d7e6928f",
    "content_type": null,
    "category": "미분류",
    "tags": [
      "윤회와 전생",
      "수행",
      "분노",
      "존재와 죽음"
    ],
    "chunk_index": 0,
    "chunk_info": "청크 1 (문단 1)",
    "paragraph_indices": [
      0
    ],
    "total_chunks": 1,
    "chunk_id": "advanced/012. 을동2  공도사상.rtf_chunk_0",
    "source_file": "advanced/012. 을동2  공도사상.rtf"
  },
  "tagging_time": "2025-05-05T00:21:45.739169",
  "auto_generated": true
}