{
  "document_id": "0afb26a0-426d-4583-8645-2ee2df270e23_21",
  "file": "0afb26a0-426d-4583-8645-2ee2df270e23_21",
  "tags": {
    "자연": 0.6
  },
  "metadata": {
    "source": "",
    "filename": "",
    "label": "",
    "chunk_index": 21
  },
  "tagging_time": "2025-05-07T22:24:40.816315",
  "auto_generated": true,
  "page_content": ". (clap) 그걸 바르 게 깨쳐가지고 남한테 덕 되게 하고자 하는 자는 누구든지 대자연이 스스로 도울 것이고, 어. 스 스로 도울 겁니다. 그것이 니가 이런 연장이 필요하다면 이런 걸 줄 것이고, 천기가 연장으로 필 요하면 천기를 줄 것이고, 니가 하고자 하는대로 전부다 줄 겁니다. 하지만 남에게 덕되게 살려고 노력 안하는 자가 천기를 받을라고 니가 그렇게 노력을 한다든지, 너는 죽었습니다. 대자연이 섣 부르게 그냥 기운이 돌아다니지 않습니다. 니가 탁한, 탁한 생각으로 기운을 부르면 정확하게 탁 한 기운이 오고, 맑은 기운으로 각을 놓아 기운을 땡기면 정확하게 맑은 기운이 오는 겁니다. 그 러고 맑은 기운은 니가 각을 놓지 않아도 스스로 동하는 겁니다. 스스로 동하는데 니가 오라고 마 라고 앉아가꼬 오라할 거 없다. 오라하는 그 자체는 탁한 각을 일으킨 겁니다. 대자연은 니가 바 르게 살아나가는 사람은 뭘 달라고 안 해도 스스로 동한다. 그 기운이. 뭐를 얻기 위해서 아, 이 러고 뭐를 얻, 이거는 무조건 탁한 기운을 땡기고 있음을 알면 됩니다. 안 주는 걸 왜 달라하노. 안 주는 걸 왜 달라고 하느냐고. 그걸 얻을라꼬 환장을 하느냐고. 대자연은 스스로 있고, 천지기 운은 가만히 계시사, 인이 동한다. 응? 그, 요 천부경에 써 놓은 소립니다. 이게. 어? 어. 천이삼 지이삼 인이 이삼 하나니라. 어. 인이 이삼한다. 천지 기운은 가만히 계시사 인이 운용을 하는 것 이다. 대자연의 기운은 가만히 있습니다. 너희들이 운용하는 거니까. 어. 너희들 각에 달렸다. 너 희들 생각을 어떻게 하느냐 따라서 이 기운"
}