{
  "document_id": "18034397-dbb6-4b73-af80-4def4faaff95_6",
  "file": "18034397-dbb6-4b73-af80-4def4faaff95_6",
  "tags": {},
  "metadata": {
    "source": "",
    "filename": "",
    "label": "",
    "chunk_index": 6
  },
  "tagging_time": "2025-05-07T22:00:28.216641",
  "auto_generated": true,
  "page_content": "더 잘 되게 하면 안돼요. 내가 쫓아가야 돼요.” 이카고 “내가 쫓아가 게, 쫓아가게 해주세요.” 이카고. 내가 가야 되는데. 남편을 자꾸 올리달라는 거예요. 어, 이 원리를 잘 이해를 해봐요. 이 말을 듣고. 그잉께 남편을 자꾸 올리달라고 하니까 자꾸 올려 주니까 나는 땅바닥에서 아무것도 안 갖췄으니까 인자 말이 안통하니까 느그는 헤어지든지 느그는 아주 멸시를 당하든지 에? 아, 이런 이런 지금 우리가 그런 짓을 했다는 얘기예요. 음. “하여튼 우리 자식 저 이 저 뭐 어데 합격되게 해주세요.” 뭐 또 빌었고 뭐 이카니 자 꾸 합격되가 자꾸 올러갔어요. 어 난중에 요만큼 올러가고나니깐 이게 와가주고 뭐라고 하 는 게 “엄마는 뭔 그런 말을 해쌓는데.” 말이 안된다는 얘기예요. 하니께 엄마하고 멀어지 지. “하... 내가 너를 잘 저 이게 합격해게 할라고 얼마나 빌었는데.” 빌었지. 거 합격됐잖 아. 그랬는데 뭐 어옜단 말이고. 어 합격됐는데 어옜단 말이에요. 에. 이게 자식이 이렇게 거 거 대학을 나오고 자식이 아 무슨 많은 그 저 이 인기인이 되고 이렇게 돼버리면 집에 와갖고. 아부지 엄마요? 콧방구 껴요. 말이 저거 수준하고 안맞다는 겁니다. 어. 지금 그짓 을 우리가 했다는 얘기예요. 어? 안했어요? (했습니다.) 인자는 우리가 이런 걸 바르게 앎으 로써 내 잘못이 뭐였었구나. 인자 이걸 짚을 수 있는 겁니다. 내가 잘못을 했는데 큰 소리 치믄 너는 더 힘들어진다는 사실이거든요. 잘못을 핸 기 있다면 지금부터라도 쪼끔이라도 나를 갖출라고 노력해야 되고. 방법은 두 방법이 없어요. (2편에서 계속..."
}