{
  "document_id": "186158ab-0b26-4f23-a2b7-e107c001981c_0",
  "file": "186158ab-0b26-4f23-a2b7-e107c001981c_0",
  "tags": {
    "경제": 0.6,
    "교육": 0.6
  },
  "metadata": {
    "source": "",
    "filename": "",
    "label": "",
    "chunk_index": 0
  },
  "tagging_time": "2025-05-07T22:24:43.105193",
  "auto_generated": true,
  "page_content": "37강 조기 경제교육-1(1/2) 질문 : 자녀의 경제 교육은 빠르면 빠를수록 좋다고 하거든요. 근데 제가 생각하기에는 어 릴 적부터 이렇게 뭐든지 돈으로 가지고 계산을 하게 되면 아이가 크면서 너무 이기적이 되 고 긍까 계산적으로 될 것 같은데 그 아이의 경제 교육은 언제부터 시작을 해야 되는지요? 경제교육. (예.) 영재교육이 아니고 경제교육? 아이들한테 경제교육을 왜 시키나? 질문 : 요즘 또 부자 아빠 가난한 아빠 이런 식으로 해가지고요. 애들한테 돈을 줘서 경제 를 자기가 쓰게끔도 하구요. 막 이렇게 예를 들어 얼마씩 줘서 돈을 관리 이걸 경제교육이 라고 붐처럼 일어가지고.... 아, 그걸 보고 경제교육이라 그러는 거야? 그게 어째 경제교육이 되나? 돈 쓰는 방법을 아 리켜주는 거지. 아니 돈 쓰는 방법을 아리켜주는 거 아녜요. 뭐 수입 이꼬르 뭐 이래 이게 아니잖아. 질문 : 아니. 어떤 사람들은요, 주식투자를 하게끔도 해요. 그래서 돈을 버는 방법도 알려주 거든요? 아주 세상 어떻게 그 그건 노름꾼 만드는 거죠. 어? 아이들한테 앞으로 돈 버는 방법 알켜 주면 안 돼요. 버는 방법은 안 돼. 쓰는 방법은 아리켜줘도. 버는 방법은 안 된다고. 이건 경제교육이 아니에요. 어릴 때부터 주식 그 이걸 아리켜주면요, 주식 같은 거, 돈 버는 방법 을 아리켜주면 애들이 그 동작이(*) 굉장히 빨라져 버립니다. 어. 다른 건 다 놔버려요. 어. 가다보면 다른 건 다 놔버려요. 어. 큰 일 나죠. 지식인 안 돼죠. 어? 노름꾼 되지. 어? 질문 : 경제인은 되지 않을까요? 참 말... 내 경제인 되는 방법을 아"
}