{
  "document_id": "1a284006-dc19-4bc7-baed-f87aed8ea8b6_1",
  "file": "1a284006-dc19-4bc7-baed-f87aed8ea8b6_1",
  "tags": {},
  "metadata": {
    "source": "",
    "filename": "",
    "label": "",
    "chunk_index": 1
  },
  "tagging_time": "2025-05-07T22:00:30.473353",
  "auto_generated": true,
  "page_content": "위의 사람들이고. 70%가 이 분들은 윤회를 한 번 더 할 수 있는 사람들이고, 또 30%는, 70% 중에서 반은 윤회를 한 번 더 하고, 반은 윤회를 두 번 더 할 수 있습니다. 이 민족이. 여러 분 30%는 윤회를 할 수 없다라는 게 문제입니다. 두 번 다시 인육을 쓰고 3차원의 세상에는 절 대 오지 않는다. 이거 꼭 알아야 됩니다. 인자. 이 민족은 내가 누구인지를 분명히 알아야 됩니다. 너희들은 윤회가 끝났다. 이 마지막 일생이다. 이 육신을 한 번 더 갖고 싶어도 못 갖는. 아주 소 중한 것입니다. 엄청나게 중요합니다. 그런데 이걸 함부레 쓰고 가버리면 너는 후회해도 소용없습 니다. 영혼 세상에 가가꼬 니가 후회를 아무리 해도 그래서 이승에서 저승보다 뭐가 낫다고? 그 렇지. 개똥밭에 굴러도 이승이 낫다고. 그 소리가 여기 있습니다. 윤회를 하는 데서는 그 소리가 안 나옵니다. 이 민족의 단어입니다. 그게. 어떤 민족도 이 소리는 안 씁니다. 이 민족만 이 단어 를 씁니다. 죽어가꼬 영혼들까지 자손들한테 그렇게 선몽을 주매 올까. 영적으로도 그렇게 이야기 합니다. 육신을 받아가 한 번만 더 갈 수 있다면. 이 소리를 합니다. 기회가 없습니다. 우리가 이 걸 모르고 지금 살고 있다는 게 문제입니다. 이 육신 마지막 일생은 엄청나게 소중하게 써야되는 것입니다. 헌데, 이 반비례하면서 우리는 어려운 사람들 꺼를 전부다 우리가, 우리 가족이 챙겨 와가지고 내 아이를 대학도 보내고, 조건을 맞추어서 아주 때때옷도 사입히고. 이거 옛날 버전인 가? 그런 것도 할 수 있습니다. 자가용도 사주고, 스키도 타러 가라"
}