{
  "document_id": "20a073cf-3e42-4f6e-9f4a-29aaf036ed24_4",
  "file": "20a073cf-3e42-4f6e-9f4a-29aaf036ed24_4",
  "tags": {},
  "metadata": {
    "source": "",
    "filename": "",
    "label": "",
    "chunk_index": 4
  },
  "tagging_time": "2025-05-07T22:24:38.257848",
  "auto_generated": true,
  "page_content": "은 그 직원 쪼끔 이렇게 우리가 맻 년만 잘 돌아가면은 사장님은 땅도 사고 집도 열 채도 사고 오만 거 다 할 수 있습니다. 어. 벤소도 사도 되고 내 집에 아들도 뭐 차도 사줘도 되고. 다 되는데. 이 종업원들이 이게 내려가면 내려갈수록 관료라든지 고 밑에 층은 이게 내려가면 내려갈수록 아주 뭐, 뭐 내가 17년, 20년 해도 집 한 채 살지 말지, 말지 한단 말이죠. 사 장님은 3년만 이거 내 꺼를 챙겨가도 집은 열 채도 삽니다. 땅도 더 사놀 수 있고. 어, 이 게 인자 경제가 불어나죠. 엄청나게 불어나는데. 내려가 밑에는 맻십 년 해도 십맻 년 이십 년을 해도 집 한 채가 마련될지 말지거든요. 그것도 아껴야 그래 되는 거지. 사장님처럼 먹 었다가는 택 반 푼도 없습니다. 50년 가도 집 못 마련합니다. 요런 구조적인 데에 우리는 백성들을 뭐라 카면 안 된다라는 거죠. 어, 지도부가. 어. 근데 요런 것들이 지금 현재 우리 가중소기업을 한다든지 이런 분들이 이런 걸 굉장히 몸으로 치이고 있습니다. 아, 그 이 저 지도층들이. 몸으로 치이고 있는데, 백성들은 당신이 됐든 그 사람이 됐든 상관없이 지도층 에다가 지금 뭔갈 요구를 하고 잣대를 갖다대고 어, 아주 신용을 안하는 겁니다. 어. 이 세 상이 지금 요, 요런 것들이 지금 계산할 때가 돼버렸기 때문이거든요. 어. 헌데 이 지금 일 하는 사람을 뭐라 카는 법은 없습니다. 우리가 뭔가 잘못하고 있지 않느냐? 우리가 지금 그 종업원들한테 어, 안 좋은 소리를 들으면 누가 마음이 아픕니까? 한번 요 요거 한 번 짚어 봅시다. 종업원들은 저 아랫 람들은 막 그"
}