{
  "document_id": "23e399e0-4577-4c03-a839-27e0536f632c_30",
  "file": "23e399e0-4577-4c03-a839-27e0536f632c_30",
  "tags": {
    "문학": 0.6
  },
  "metadata": {
    "source": "",
    "filename": "",
    "label": "",
    "chunk_index": 30
  },
  "tagging_time": "2025-05-07T22:00:23.224240",
  "auto_generated": true,
  "page_content": "니다. 이때까지 너무 모르고 우리가 사는 겁니다. 이렇게 해서 내조라는 것은 서로가 말이 통해야 돼. 남자가 밖에서 일을 하는 동안에 3년간은 니 한테 기회를 줍니다. 결혼을 딱 하면 정확한 기회를 주는 것은 결혼을 딱 하면 남자는 열심히 일 을 하고 너는 안에서 시간이 많습니다. 이 많게 해 준 건, 대자연은 너희들을 놀게끔 이 3차원에 보내질 않았습니다. 우리는 죄인들입니다. 놀 수 있는 시간은 정확하게 준 적이 없습니다. 한데 나는 놀았다. 저 사람은 열심히 할라고 노력을 했고 나는 놀았다면 니 갖춤을 갖지 못해가지고 이 것은 정확하게 내한테 돌아옵니다. 그러니 결혼을 시키는데에 내조 공부를 시킨다매 된장찌개만 잘 끼리고, 밥 잘하고, 빨래 잘 하고, 남편 속옷 잘 챙겨주고, 뭐 여게 안 섞이고, 저게 안 섞여야 된다 그러고 이런 거만 가르켜가 보냈다면 그거는 무조건 지금, 지금 이 세상에는 정확하게 이혼 을 합니다. 전에 우리 세상에는 그렇게 안했습니다. 눈 감기고, 가루코 이래가꼬 델꼬 가라가지고 니가 나가면 굶어 죽게끔 만들어가지고 델꼬 있었습니다. 내가 인제 나가가 뭐하겠노. 바보를 만 들었습니다. 배움도 못 배우게 했고, 나가가꼬 말 상대도 못하게 했고, 주디도 틀어 막았고, 나가 봐야 할 짓이 없고 굶어 죽게 생겼으니까 어차피 빌붙어 있게끔 만들어가꼬 그 설움, 설움 다 겪 으며 살게 만들어놨지만 지금은 방목 시댑니다. 방목. 오픈해놨어. 내가 그래가꼬 밖에서 문을 딱 잠구면 텔레비전까지 꺼내가 가야 돼. 어. 텔레비전 놔뒀다면 그 안에가 바깥이여. 틀면 다 나와. 정보가 홍수된 시댑니다. 세"
}