{
  "document_id": "28032464-08a2-4d53-b733-327afe45fc2b_16",
  "file": "28032464-08a2-4d53-b733-327afe45fc2b_16",
  "tags": {},
  "metadata": {
    "source": "",
    "filename": "",
    "label": "",
    "chunk_index": 16
  },
  "tagging_time": "2025-05-07T22:24:46.340811",
  "auto_generated": true,
  "page_content": "된 사람이 많이 나오면 많이 나올수록 우리 삶은 어려워집 니다. 어떤 방법으로 이게 경제가 이동수단을 갖던 우리가 몸소 치러야 할 일이 많이 생기 든 우리는 알게 모르게 어떤 단체들이 어떤 집단들이 어떠하게 이렇게 방편으로 이런 방법 저런 방법으로 하지만 결국은 우리 국민들이 전부다 같이 힘이 들어 가가지고 그것이 전부 다 다스려지는 겁니다. 그러니까 직접적으로 나한테 돈 내. 안 했다고 해서 우리가 안 나가 는 게 아니고 전부다 이 사회가 어려워지면 그걸 갖다가 매워놓는 것은 국민 세금으로 해야 되고 국민들이 지금 어디에다가 많이 주는 것으로 갖고 조금씩 떼어줘도 주고. 그러니까 기 업한테 지금 많이 주면 기업이 지금 여기에 직접 안 나옵니다. 기업한테 우리가 만일에 예 를 들어가지고 1억을 주었다면 1억을 갖다가 사회에다가 환원을 못합니다. 기업에다가 1억 을 주면 정확하게 93%정도를 기업을 키우고 그쪽에 또 좀 불려놓고 뭐 이런 데 하는데 쓰고 한 7%. 많이 내놔도 7%정도만 사회에다가 지금 뿌립니다. 그럼 그 돈은 없어졌느냐? 없어진 것은 아닙니다. 모이고 있다는 거죠. 모이고 있다. 그래서 기업은 커지는 겁니다. 그래서 시간이 지나니까 저거는 4조원짜리가 조금 한 4,5년 지나니까 20조원이 되고. 거기다가 한 7년 더 지나니까 뭐 한 60조 기업이 되고. 이렇게 자꾸 불어나는 겁니다. 왜? 국민들의 피땀을 자꾸 거기다가 지금 축적시켜놓는 거예요. 이 원리를 조금 있다가 이 야기를 하겠지만 이 원리를 어떻게 풀려... 왜 그렇게 되고 있는가를 전부다 풀어야 됩니 다. 정확하게 풀어야지 ‘어 맞다."
}