{
  "document_id": "28e29b7e-fe4b-43f1-8d82-3ef0b78b6edd_22",
  "file": "28e29b7e-fe4b-43f1-8d82-3ef0b78b6edd_22",
  "tags": {},
  "metadata": {
    "source": "",
    "filename": "",
    "label": "",
    "chunk_index": 22
  },
  "tagging_time": "2025-05-07T22:24:44.298180",
  "auto_generated": true,
  "page_content": "시점이라고만 분별할 뿐 이 사춘기가 왜 오는지, 사춘기가 무 엇인지도 모르고 우리는 그냥 막연하게 살아왔던 것 같습니다. 선생님 그 사춘기라는 것은 도대체 무엇을 뜻하는 것이며, 이 그냥 술술 인생살이 할 수도 있겠는데 왜 꼭 이런 사춘기를 거치고 넘 어가야만 하는지 우선 요 부분부터 일깨워 주십시오. 51분 30 사춘기란 사람마다의 오는 나이는 다릅니다. 사춘기가 언제 왜 들어오느냐? 기운이 바뀔 때입니 다. 사람이 성장기에 한 번, 두 번 , 세 번 기운이 바뀝니다. 바뀔 때마다 기운이 달리 들어오니까 이게 기운을, 지금 여기에 따라서 내가 움직이는 겁니다. 그럴 때 되변 기운이 한번 바뀔 때 되 면, 아주 미운 일곱 살이라 그러죠? 요때 기운이 한번 바뀝니다. 그리고 2×7에 14, 14살에서 안 팎으로 기운이 바뀝니다. 근께 7년에 한번씩 바뀐다 라는 소리입니다. 그래서 3×7에 21, 그 기운 을 완성하는 겁니다. 그래서 교육은 21세까지 키워서 성인으로 시켜내야 되는 게 교육입니다. 그 래서 성인으로 똑바르게 키웠다면 이 자는 성인이 되지 중생이 아닙니다. (53분 인간에서) 인간이 라는 단어에서 벗어나서 성인이라는 단어가 됩니다. 인간이라고 하는 것하고 사람하고 같은 줄 알 지만 사람하고 인간은 틀립니다. 지금 착각들하고 있던 겁니다. 그 원리가 큰 원리가 없기 때문에 근본의 원리가 없어서 우리는 혼동하고 쓰는 단어들이 너무 많습니다. 인간이라는 것은 間(사이 간)자를 써서 사람도 아니고, 동물도 아닌 인간입니다. 그것이 중생입니다. 그것은 어린아이일 때 도 인간이고, 자라 나갖고도 인간입니다."
}