{
  "document_id": "328145a6-960b-4ae8-9672-e7e520f8e9c0_6",
  "file": "328145a6-960b-4ae8-9672-e7e520f8e9c0_6",
  "tags": {},
  "metadata": {
    "source": "",
    "filename": "",
    "label": "",
    "chunk_index": 6
  },
  "tagging_time": "2025-05-07T22:00:21.929408",
  "auto_generated": true,
  "page_content": "롷게 하면 정부에서도 이 키를 잡게 해줄 것이고. 에? 모든 기업에서도 이 키를 잡게 해줄 것이고. 이런 걸 해가주고 그때를 위해가주고 지금 나를 갖 춧기 시작해라. 갖춧고 나면 분명히 이 대한민국이 크게 힘을 써야될 때, 당신들이 필요로 하는 사람들이니까. 내를 안 갖춧고 어영부영하고 있으면, 나는 어데 못드갑니다. 어? 즐거 운 일을 찾지를 몬해. 아. 항께 진짜로 즐거운 일을 인자 하게 될테니까. 의? 고생 끝에 낙 이 와야지. 아. 하니께 인자 너무 걱정 안 해도 됩니다. (박수)"
}