{
  "document_id": "36e407a1-2171-4f7f-b5f3-7925ee9c27db_26",
  "file": "36e407a1-2171-4f7f-b5f3-7925ee9c27db_26",
  "tags": {
    "사회": 0.6
  },
  "metadata": {
    "source": "",
    "filename": "",
    "label": "",
    "chunk_index": 26
  },
  "tagging_time": "2025-05-07T22:00:32.321700",
  "auto_generated": true,
  "page_content": "을 읽거나 고행하는 것이 아니다. 바른 수행이란 세상 속에 서 문제의 답을 찾아 사람들에게 전달하고, 이를 통해 사회를 이롭게 하는 활동이다. 이렇게 공덕을 쌓은 자는 다 음 생에 보다 나은 환경에서 태어나게 된다. 고행은 수행이 아니다 과거에는 잠을 자지 않거나 굶는 고행이 수행이라 여겨졌으나, 이는 고집스런 방식일 뿐 참 된 수행이 아니다. 신체를 혹사하는 고행은 사회에 아무런 기여도 하지 못하며, 후세에 공덕으로 작용하지 않는다. 신통력과 수행은 다르다 차원세계나 신과의 교신을 통해 신통력을 얻는 것과 수행은 본질적으로 다르다. 신통은 재주에 불과하며, 진정한 깨달음은 지식을 갖추고 세상에 도움이 되는 공덕을 쌓는 데서 비롯된다. 능력이 있다고 깨달은 자는 아니다. 윤회는 공덕의 반영이다 이번 생에서 많은 공덕을 쌓은 자는 다음 생에 더 나은 조건으로 태어난다. 반대로 아무런 공덕도 없이 죽으면 다음 생은 하층 조건에서 다시 시작된다. 이는 수행과 삶의 결과가 전생과 다음 생을 이어주는 법칙이다. 지식인은 최고의 수행자다 오늘날 진짜 수행자는 사회적 지식을 갖춘 지식인들이다. 이들이 진정으로 깨우치면 선 지식이 되어 세상을 바르게 이끌 수 있다. 이제는 지식인들이 수행을 마무리하고 깨달음을 얻어야 할 시점이다. 공덕은 사회적 실천에서 비롯된다 수행자는 세상을 정리할 답을 제시하고 실천하여 사람들에게 도움이 되어야 한 다. 그 공덕이 쌓이면 다음 생에도 좋은 인연과 환경을 얻게 된다. 이는 수행이 신비주의가 아니라 실천의 영역임 을 말한다. 지금까지의 수행은 연습이었다 과거의 다양한 수행 방식들은 연습에"
}