{
  "document_id": "38cc091b-5808-4882-82ee-cce9c5580a90_20",
  "file": "38cc091b-5808-4882-82ee-cce9c5580a90_20",
  "tags": {
    "문학": 0.6
  },
  "metadata": {
    "source": "",
    "filename": "",
    "label": "",
    "chunk_index": 20
  },
  "tagging_time": "2025-05-07T22:24:45.458629",
  "auto_generated": true,
  "page_content": "이에요. 조디만 살아가꼬 그러잖아. 왜. 입이 살아있는 민족이 이 민족이에요. 응. 말도 야물게도 잘 한다. 이거는 일꾼이거든. 요건. 근데 이게 인자 이 사람이 말 을 잘 할려면 프로그램이 좋아야 되는데, 어, 내가 이거 저 장착핸 프로그램이 좋아야 요기 싹 나 올 때 잘 해가 나오는데, 프로그램을 문디같이 넣어 놓은 거라. 이게. 지금 그래서 다 어려움을 겪는 거에요. 대화가 잘 안 되는 거라. 프로그램 꺼내가 그거갖고 할라하니 지금 내 앞으로 온 인 연한테 이기 뭐가 안 맞는 거에요. 이게. 그, 전부 교육이 주입식 교육이 됐고, 답을 내 놓은 걸 갖고 맞다, 아니다 요러고 해 놨으니까. 이러면서 배우고 공부를 해 왔으니까. 응. 우리가 앞으로 요, 요, 지금 몇 분들 계시지. 유치원 경영하시는 분들. 어린이 아리키는데 주입식 공부를 시키면 절대 안 되는 거라. 유치원을 가르킬 때는 모든지 피부도 접촉 하고, 뭐 장난감도 가지고 놀고, 모든 사물을 자꾸 접하게만 해줘버리면 가들 공부는 끝나요. 아주 신체적으로 발달이 덜 됐응께 자빠져가꼬 대가리를 콱 안 지박을란가 요런 거만 잘 챙겨가면서. 뭐 자꾸 가주 놀 걸 새롭게 가 주 놀 걸 자꾸 이렇게 대만주면 아주 그러면 공부가 끝나는 거에요. 그게. 최고의 공부법입니다. 기초공부를 하고 있는 중인데 거게다 주입을 시켭버리면 딴 답은 맥히죠. 기초때는 표가 안 나는 거에요. 전부다 지금 이 센서에다가 지금 갖다 넣고 있는 중이라. 이게. 오만 걸 다 갖다 넣는데 이 때 능력은 어마어마 해 집니다. 한데 지금 주입시킬라 그래. 이거는 오리. 그게 오리라고 누가"
}