{
  "document_id": "450de7b1-f478-446a-8bb6-a11dd4ce6396_17",
  "file": "450de7b1-f478-446a-8bb6-a11dd4ce6396_17",
  "tags": {},
  "metadata": {
    "source": "",
    "filename": "",
    "label": "",
    "chunk_index": 17
  },
  "tagging_time": "2025-05-07T22:24:38.294505",
  "auto_generated": true,
  "page_content": "법인데, 우리가 스 스로 낮춰버리니까 가마 시간 지나다 보니까 위에 사람 안 같으니까 그냥 막 먹는 것입니다. 이 게. 그래서 우리 인성을 갖추고 인품을 갖추어서 상대를 대하면 인류에 최고의 민족이라는 거죠. 헌데 요새 그렇게 못 하고 있다는 거죠. 그렇게 해서 우리는 스스로 우리 기운을 낮췄던 것입니 다. 근데 우리가 수행자 이야기를 들어가다가, 지금 이거 전부다 수행 이야기입니다. 이 자체가. 이런 깊이를 모르던 것을 끌어내서 우리는 아는 게 수행입니다. 이 민족은 알고 나면 그 다음에 궁금하지를 안 하고 내가 그걸 사용을 하는 것입니다. 저쪽 민족들은 그걸 알고 나면 사용하기 보 다는 알고 죽으면 그 다음 생에 더 위치를 좋은 데에서 태어나기 위해서 아는 것이고, 그래서 내 생을 위해서 사는 것이 저쪽 사람들이고, 그 말들을 많이 들을 거에요. 내생을 위해서 지금 한다 라는. 그래서 지금 우리한테 도파들이 가지고 온 수행들은 전부다 내생을 위해서 하는 수행법입니 다. 내생을 위해서. 지금은 내가 이렇게 되더라도, 이렇게 해가꼬 그냥 죽을지라도 내생에는 바른 데 태어나서 바르게 하겠다라는. 그런데 이 수행법이 저쪽에서 건너왔기 때문에 그걸 그냥 받아들 였기 때문에 그런 것이다. 나를 모르고. 나를 알고 나면 그렇게 수행을 하면 안 됩니다. 이 민족 수행은 이 생에 어떻게 하면 내가 일생을 진짜로 거룩하게 바르게 모든 원한을 다 풀고 가느냐? 그렇게 수행을 해야 됩니다. 어떻게 하면 모든 이 육신에 있는 에너지, 내한테 준 시간 에너지를 모두 불을 태우고 가느냐? 2등은 필요가 없어요. 다음에 내가 경기"
}