{
  "document_id": "53b6edb6-50fa-4671-8801-c3105dd00a40_26",
  "file": "53b6edb6-50fa-4671-8801-c3105dd00a40_26",
  "tags": {
    "소통": 0.6,
    "문학": 0.6
  },
  "metadata": {
    "source": "",
    "filename": "",
    "label": "",
    "chunk_index": 26
  },
  "tagging_time": "2025-05-07T22:00:22.224535",
  "auto_generated": true,
  "page_content": "보고 아니면 파트너를 바꾸든지 아니면 여기서 정리를 하던지 아니면 요렇게 해가 지고 요렇게 어떻게 해 빨리 해나가야지 더 이상의 에너지 손실을 안 합니다. 사람이 말이 막히면, 기술자하고 운영자하고 말이 딱 막히면 그건 무조건 망합니다. 끌고 가면 갈수록 망합니다. 대화소통이 막혔다라는 것은 너희 동업자라는 것은 끝났다라는 것입니다. 어떤 사업을 하던지 동업을 하는데 말이 막혀가지고 저 사람 비밀이 따로 있고 내 비밀이 따로 있어 가지고 지금 이렇게 뭔가를 따로 이렇게 하고 있다면 무조건 중단을 하고 다시 생각해봐야 합니다. 그래가지고 여기에서 소통을 키워내든지 예 아니면 접어야 됩니다. 다 시 뿜빠이 해가지고 접어가지고 솔로로 가든지 뚜엣으로 다시 만나든지 예 이것은 무조건 정해야 됩니다. 정해야 되고, 우리 부부도 마찬가지입니다. 부부도 말이 딱 막혔다 빨리 정 리를 해갖고 우리 말을 소통을 시킬려고 달라들어야 됩니다. 말을. 대화로 소통을 못시키면 너희는 가면 갈수록 지금 망하는 길로 가고 있습니다. 언제 터져도 터집니다. 인생은 인생 대로 다버려놓고 터집니다. 정 안되면 네 입으로 찍어가지고 결국은 차사고까지 나게 해가 지고 신랑부터 보내든지 부인부터 보내든지 해서라도 헤어집니다. 말이 막히면 안됩니다. 그러면 너는 동업자로써 끝난 겁니다. 이것은 말을 빨리 소통을 시켜서, 처음에 이게 막히 면 소통 시킬 수 있는 그러한 것이 많습니다. 그때는 나를 조금만 이렇게 노력을 내를 내가 낮추는 것은 노력이 필요합니다. 조금만 딱 필요할 때 그때 조금만 내가 낮춰가지고 그 상 대의 마음을 먼저 어루만져서 들어"
}