{
  "document_id": "5e3df593-74f6-44ab-808d-1983472d63bc_7",
  "file": "5e3df593-74f6-44ab-808d-1983472d63bc_7",
  "tags": {},
  "metadata": {
    "source": "",
    "filename": "",
    "label": "",
    "chunk_index": 7
  },
  "tagging_time": "2025-05-07T22:24:48.307104",
  "auto_generated": true,
  "page_content": "게 안 되었습니다. 88올림픽 때 모일 수 있는 건 다 모였던 겁니다. 싹 들어 와가지고 세상에서 우수하다는 것은 다 들 어 와갖고 그게 대표들로 들어온 겁니다. 국제사절. 뿌리 살리기 프로젝트 성공. 그때 뿌리 살리기는 끝났던 겁니다. 너희가 필요한 물자도 다 주었고 너희가 필요한 교과서도 여 다 들어왔고 이 사상이 들어온 게 교과서입니다. 멀리 있다고 못 봐서 못 했다는 소리는 하지 마라. 이 나라 안에 다 들라 줬으니까. 인자는 너희가 이걸 다 뒤져보고 니가 알아서 해라 는 거라. 그래서 전부다 1등하는 것들이 막 만세라고 부르고 경기 하나 끝나면 만세 부르 고. 끝났다는 겁니다. 폭죽을 터주코 난리가 났죠. 우리나라에서 그런 난리는 처음 난 겁니 다. 난리가 나가지고 전부다 이렇게 만세 부르고 끝났다. 프로젝트 성공한 겁니다. 근데 이 깊이를 우리는 모르고 있었다. 이걸 깨우친 사람이 없다. 그러니 깨우친 사람이 없으니까 어떻게 됐냐? 그때까지 해준 것이 인류에서 우리가 필요한 앞으로 너희들이 일할 수 있는 필요한 이 힘은 다 준 겁니다. 원조라는 힘으로. 돕는다는 힘으로. 다 주었습니다. 양보라 는 힘으로. 다 주었는데 사상도 다 주었고 그걸 다 주었는데 이걸 어떻게 썼느냐? 모르다보 니까 이제는 우리가 살판이 났다는 겁니다. 살판이 났지. 그래갖고 여행 다니고 골프 치러 다니고 뭐 스키 타러 다니고 아주 신났지. 물자가 좀 많은께. 어디 써야 될지 그 근본을 몰 랐던 겁니다. 신났지. 잘 놀았지. 놀다가 보니까 어떤 일이 터졌냐? 실큰 쓰다보니까 기업 하는 사람도 이게 좋은가? 이게 장땡인가? 쪼다"
}