{
  "document_id": "6d1de6b6-70c0-4ad7-b7e1-feb6dd775440_5",
  "file": "6d1de6b6-70c0-4ad7-b7e1-feb6dd775440_5",
  "tags": {},
  "metadata": {
    "source": "",
    "filename": "",
    "label": "",
    "chunk_index": 5
  },
  "tagging_time": "2025-05-07T22:24:46.451343",
  "auto_generated": true,
  "page_content": "겁니다. 에? 바베큐고 이런 거는 서 양사람들한테 맞는 거야. 왜냐. 기운을 쓰는 사람들은 근육을 챙겨야 되고, 어, 그러고 탁한 일을 하는 사람은 탁한게 내가 가는 겁니다. 그렇게 해서 그런 것들 막 피가 질질 흐르는 걸 주 먹어야 되고, 이런 거는 지도자는 그런 짓 안 합니다. 니 품성을 바르게 갖춰지면 어. 절대로 그런 짓을 안 합니다. 그러니 임금 수라상에 올라가는 이 음식을 잘 보십시오. 절대로 지글지글 굽는거는 안 올라갑니다. 불을 갖다놓고 굽어 쳐먹지도 안 합니다. 절대 잘 열처리를 해가꼬 잘 삶아가지고 잘 여며서 야채하고 잘 갖다 놓으면 고걸 탁 집어서 곱게 먹지, 밥상이 절대 흩트러 지는 법이 없습 니다. 밥상을 니가 밥을 어떻게 먹느냐를 보면 너 인품을 알 수가 있습니다. 밥상에 뭐를 좋아하 고 뭐를 지금 챙기고 있는지하면은 니 품성이 그대로 다 나타납니다. 언제 보니까 누가 밥상에 도 가 있다 이래가꼬 “어? 이 사람들이 뭘 아나?” 싶어가꼬 내가 이래 보니까 들어가보니까 밥상에 도가 있다 하더니만 한다는 소리가 들어가보니 그 소리가 아니고 아, 이거 맛있고, 맛을 아는 기 도고, 이케싸매 뭔가를 전부다 올리놓은께 뭐 돼지고기도 굽어가꼬 이래가꼬 우글우글 쳐먹으매 도가 있다 그러고. 또 내가 또 속았어. 진짜 밥상에 도가 있습니다. 뭐냐. 니 인품이 밥상에 나타 난다. 지금 우리가 뷔페가 좋다, 좋다 하는데 그건 좋은 게 아닙니다. 뷔페가 어떤 음식이냐. 내 한테 시중들 사람이 없어졌을 때 니가 직접 손으로 가서 집어 먹어야 된다는 사실입니다. 지도자 는 시중들 사람이 있어지는 법입니다."
}