{
  "document_id": "6f9790f0-0467-4b4d-8920-5e6570438261_25",
  "file": "6f9790f0-0467-4b4d-8920-5e6570438261_25",
  "tags": {},
  "metadata": {
    "source": "",
    "filename": "",
    "label": "",
    "chunk_index": 25
  },
  "tagging_time": "2025-05-07T22:24:46.620097",
  "auto_generated": true,
  "page_content": "못 사는 그 화풀이는 정확하게 부모한테 다 가온다는 걸 알고, 어, 앞으로는 어, 어린이들을 어, 우리가 다루기를 어, 조금 우리 빚쟁입 니다. 내가 저, 그, 그 자들한테 빚이 졌기 때문에 그렇게 해 줘야 될 의무를 가지고 있는 겁니다. 쌍방 빚을 가지고 있는게 부모와 자식입니다. 한데 갚는 거는 정확하게 선 갚고 후 되받는 겁니다. 이게 부모와 자식의 고립니다. 빚의 고리는 똑같은데 큰 죄를 같이 지고 있 는 겁니다. 하지만 내가 선 갚고, 자식한테는 후 빚을 받는 것입니다. 이것이 효라는 겁니 다. 내가 선 갚아냈을 때 효가 나와서 나한테 빚을 정확하게 갚아낸다. 어. 이것이지, 니가 선 빚을 갚지 않았거든 절대 빚은 0.1%도 받지를 못하게 되가 있습니다. 어? 이 분명히 알 아야 됩니다. 하니께 인자 앞으로의 우리 자식들을 다시 봐야 되고, 어, 우리가 천상에서 지 은 업, 죄 고리. 그니께 서로가 역행을 해가지고 크릭이 가서 우리 에너지가 탁해져서 30% 에너지가 탁해져서 이 지상 3차원을 형성해서 여게 와 갇혀가 있는 겁니다. 우리가 이 에너 지를 맑게끔 이렇게 정화를 해서 우리가 대원소로, 대우주의 원소로 우리는 돌아가야 될 의 무가 있고, 그기 돌아갈 때까지 이 3차원에서 윤회를 하면서 3‧4차원에서 우리 할 일을 지 금 하고 있는 겁니다. 그래서 전부 업을 소멸할 때 우리는 같이, 전부다 같이 업을 소멸을 할 때, 모두 손에 손 잡고 전부다 대우주로 그냥 싹 들어가. 내 원자리. 어, 여, 회귀. 응? 긍께 대자연, 대우주 회귀사상. 이 회귀를 우리는 할 때 자타일시 성불도라는 것이 이 단"
}