{
  "document_id": "7ce5ed41-bf87-4e75-9ad1-6bacdf8b44a3_11",
  "file": "7ce5ed41-bf87-4e75-9ad1-6bacdf8b44a3_11",
  "tags": {},
  "metadata": {
    "source": "",
    "filename": "",
    "label": "",
    "chunk_index": 11
  },
  "tagging_time": "2025-05-07T22:24:44.158362",
  "auto_generated": true,
  "page_content": "못하고 있는 겁 니다. 여러분들 지금 노력을 잘 하고 있습니다. 하는데, 방법이 조금 달랐다. 다르니까, 조금을 노력해가지고 이거하나 실천만 하십시오. 조금한거, 선생님을 위해서 그것도 못 해 주나? 그것만 실천되면 정확하게 본인들한테 기쁨을 내가 줍니다. 그 상대를 내가 다스려 놓기 때문에 당신이 조금만 노력을 했어도 상대가 딱 돌아오게끔 내가 기운을 다스려 놨기 때문에 노력 안 하는 데는 못 돌아오는 겁니다. 하니까 조금만 노력하면 상대가 돌아 오는 게, 이거 경험해보면 많을 겁니다. 탁 돌아오면 그때 기쁘니까 이제는 그걸 할 수 있는 내 자신이 변합니다. 좋은데 왜 안 하노? 해보니까는 자신이 생기고 하기 전에 그걸 바꿔보기 가 그렇게 힘들었던 겁니다. 그러니까 이제 공부하는 자세를 덕행 실천하는 마음을 조금한 거부터 한다. 이거를 우리가 명심을 하고 작은 것부터 해서, 우리 큰 거를 하려고 들면 안 됩니다. 작은 것부터 조금 실천을 해보는 이 노력만 해주면 이 덕행실천이 어느만큼 큰 기 운을 만들어 내는지는 제가 다 느끼게끔 해드리겠습니다."
}