{
  "document_id": "83a29dbc-fb33-491f-b79b-4c41b7373c8b_3",
  "file": "83a29dbc-fb33-491f-b79b-4c41b7373c8b_3",
  "tags": {},
  "metadata": {
    "source": "",
    "filename": "",
    "label": "",
    "chunk_index": 3
  },
  "tagging_time": "2025-05-07T22:24:45.076357",
  "auto_generated": true,
  "page_content": "내이 친구들을 생각해서도 안 되고 직연 뭐 직연 맞죠 지연 지연은 뭐 천천히 하는 건가고 어 고향 뭐이 이런 것도 지금 끊어야 되고 또 종교 응 내가 이런 사상에이 편해 하던 것도 끊어야 되고 모든 걸 대통령 하는 순간에는 이걸 전부 다 놔야 돼요음 그리고 동창 뭐 대통령이 동창회를 나가면 되는가 절대 안 됩니다 내가 공적인 일만 해야지 사적인 때 정확하게 전부 다 끊어내야 돼 국민의 대표성에 있는 일만 해야 되고 그런데만 참석해야 되고 그런 일을 해내야 되는 겁니다 어 그러게 그게 대통령이 대통령이 어려운게 다른게 아니고 살을 끊는 일이라는 얘기죠 공인이 최고의 공인이 됐으므로 이거를 지켜내야만 돼요 이거를 할 줄 알아야 그래야 바른 분별이 일어나고 치우치지 아니하고 정신이 산만해지지 아니하고 이렇게 해서 내가 수행할 수 있는 일이 정확하게 지혜가 열리기 시작을 하고 나라가 보인다이 말이죠 그리고 내가 대통령이 되는 순간에 나를 위해서 일한 사람들을 위해서 내가 세상을 어 저 일을 하려고 그러면 안 돼요 내가 대통령 되는데 같이 일을 했더라도이 사람들 냉철하게 보고 분별을 해야 돼 공적으로 다뤄야 된다이 말이죠 고마운 거는 고마운 거고 사적인이 마음이 흘러가서는 안 된다라는 거죠 그리고 이런 거를 선포하고 대통령을 출마를 시작을 해야지 그렇게 할 때 대통령으로서의 할 일이 내가 보입니다 그래서 어려운 거예요 그래서 형제가 부모가 이런 것도 전부다 하나의 사적인 어 우리가이 이러한 그이 인연들이 되는 거예 대통령이 되는 순간은 종교조직 믿는 사람은 내가 좋아하고 어떤 종교 믿는 사람 싫어하는 사람은 대통령이"
}