{
  "document_id": "8d99c305-8fa8-4d89-b800-c8a4924b099d_7",
  "file": "8d99c305-8fa8-4d89-b800-c8a4924b099d_7",
  "tags": {},
  "metadata": {
    "source": "",
    "filename": "",
    "label": "",
    "chunk_index": 7
  },
  "tagging_time": "2025-05-07T22:24:40.813123",
  "auto_generated": true,
  "page_content": "그렇게 해서 “아, 이렇구나.” 그러면 와서 이 사람들을 위해서 무엇을 해줄 때 이 사람들 한테 진짜 필요한 것, 지적인 것을 해줄 수 있을까. 이런 거를 내가 공부를 끝내야 되는 것입니 다. 그렇게 할 때 그 사람들이 필요한 아이템을 우리가 만들어서 줄 수가 있는 것입니다. 그렇게 해서 이런 데 지금 우리가 나가가꼬 성인이 되어서 여행을 간다. 학생이 되가꼬 여행을 간 다 이카면, 여행을 가면 그쪽에 타진을 하러 가는 것입니다. 국민성, 그 사람들의 필요성, 그 사람 들의 지적인 필요성을 뭐를 느끼는데 즈그가 할 수 없는 것이 무엇인가. 요 가지가 할 수 있는게 있고, 몸통이 할 수 있는게 있고, 뿌리가 할 수 있는게 따로 있습니다. 각 분야가 다릅니다. 헌데 우리 지금 세상의 것, 가지가 할 수 있는 것은 다 하고 있습니다. 몸통이 할 수 있는 것도 다 하 고 있습니다. 뿌리가 할 수 있는 것은 지금 하고 있지를 않는 데서 문제가 있는 것입니다. 인류에 필요한 것 뿌리에서 할 수 있는 것만 빠져가 있습니다. 지금. 이걸 우리가 지금 중심을 못 잡고 있다. 그래서 우리 교육이 어디로 가야 하는가 이 중심을 못 잡고 있는 병폐가 바로 여게 있습니 다. 나를 알고 남을 알 때 니 할 일이 나옵니다. 이런 거를 탐구를 해야 되는데, 지금 우리는 그 걸 안 하고 있는 것입니다. 그리고 외국 나가면서도 우리가 유학을 간다 뭐 조금 있다 유학 공부 를 하겠지만, 그러한 중심을 잡지 못 하고, 내가 누군지도 모르고, 내 공부 기본을 하지 않고 밖 으로 나가니까 너는 헛 돈 내버리고, 헛 시간 내버리고 와가지고 건달 되는"
}