{
  "document_id": "9febf758-f9d4-420b-8631-361aee1d8ae6_1",
  "file": "9febf758-f9d4-420b-8631-361aee1d8ae6_1",
  "tags": {},
  "metadata": {
    "source": "",
    "filename": "",
    "label": "",
    "chunk_index": 1
  },
  "tagging_time": "2025-05-07T22:24:43.907992",
  "auto_generated": true,
  "page_content": ". 지금 이걸 따라다 니면서 수없이 수천 년, 수만 년 동안 있어도 아직까지 이걸 바르게 써가지고 고 안에까지 만져서 행까지 하고 간 자가 없습니다. 이걸 보고 수행이라고 이야기들을 하, 수행에 꽃이라고 이야기들 하는데. 요걸 우리가 인자 풀어봅시다. 욕심을 낸다든지. 응. 또 화를 낸다든지. 또 어리석은 생각 을 한다든지. 이런 것은 어데서 비롯되느냐. 내 인생을 바르게 사는 기 어데 있느냐를 모를 때. 또 내 인연이 요 앞에 왜 왔느냐를 깊이를 모를 때. 어. 모릅니다. 저 사람이 내를 내한테 화를 내는데 화내는 것 그 안에 그 깊이를 모를 때. 이럴 때 내가 반사로 나오는 것들입니다. 응? 반사 로 나온다. 어. 저, 내한테 저 사람이 악하게 대하는데 악하게 대하는 게 무언지를 나는 모를 때, 깊이를 모를 때 그럴 때 나오는 것입니다. 여러분들이 어려워졌는데, 어려운 기 왜 왔는지를 내가 모를 때. 깊이를 모를 때. 나한테 어려운 것이 하나도 안 오면 화 안 나죠? 나한테 나쁜 행위가 하나도 안 들어오면 화 안 납니다. 화를 없애라고 이야기할 게 아니고 그런 탐‧진‧치를 없애라고 이야기해서는 없어지지 않는다라는 겁니다. 니가 없앨라고 아무리 노력을 해도 그런 식으로 수행 해가꼬는 없어지지를 않는 게 바로 그 근본입니다. 그럼 그걸 없애려면 어떤 수련을 해야 되느냐. 니가 앉아서 300년 앉아 있어도 안 됩니다. 그런 걸 내는 안 해야지. 안 해야지. 이러고 3000년 앉아 있어도 이거는 안 없어집니다. 니 앞에 희한한 게 니 근기에 맞게끔 딱 와서 니가 이해하지 못할 짓을 하면 니가 참을 만치 도가 넘으"
}