{
  "document_id": "a416bcdd-581f-4724-b6cb-f3e161cfc9c2_43",
  "file": "a416bcdd-581f-4724-b6cb-f3e161cfc9c2_43",
  "tags": {},
  "metadata": {
    "source": "",
    "filename": "",
    "label": "",
    "chunk_index": 43
  },
  "tagging_time": "2025-05-07T22:24:45.440479",
  "auto_generated": true,
  "page_content": "됩니다. 왜 인연들을 위 해서 니가 살지 않으면 아니되는 근본이 어데있는 가를 우리는 알아야 된다라는 겁니다. 이게 천 부경 속에 전부다 이거 써 논 겁니다. 이거. 농축시켜 압축적으로 지금 써 놨는데 이걸 풀면 세상 의 모든 법도로 변합니다. 그래서 8차원의 기운과 9차원의 기운과 이런 것들은 전부다 니 삶 속 에서 나와가지고 스스로 만들어지는 에너지 차원입니다. 그래서 차원수. 차원수 안에 우리가 인자 풀어논 데 보면 차원수 안에 몇 차원은 어떻게 돼서 나오는 물질이며, 무, 기운 이며, 어떻게 해 서 빚어지는 기운이고, 이런 거를 다 나열을 해 놨습니다. 어. 그렇게 해가지고 칠팔구운이라. ‘6’ 인데, ‘6’인데. 생 칠팔구운이니라. 인자는 니 인생을 살아가지고 이 지상에서 떠나는 것을 이야기 합니다. 이 지상 3차원에서 니가 벗어나는 길이 이 길이라는 걸 이야기 하는 겁니다. 지상에서 니 가 이거 말고는 벗어날 외통수. 벗어날 길이 없다. 돈을 주면서 아무리 뚜드리 패고 목탁을 뚜드 리패도 절대 이 3차원 궤짝 안에서 감방에서 니가 못 나간다라는 이야기를 여게다 정확하게 써 놨으니까 인자는 천도한다, 우리 여, 우리 조상님들 어데로 보낼 생각 하지 말고. 못 가. 어. 못 가니까 보낼라고 하지 말라. 이, 난중에 내가 인자 그 분들을 돕는 방법들은 내가 알키줄테니까. 돕는 방법이 있어요. 조상님들 진짜 위하는 길을 우리가 알고 진짜 위해드려야지, 천지도 모르고 가라 이케뿔면 가는가 싶어가꼬 돈 퍼붓고 가라하면 가는가 싶어가 천지에 그런 법은 없다 이거 야. 인자 그런데 현혹되면 안 됩니다. (예)"
}