{
  "document_id": "a9e28e47-2b12-4b48-a9b5-c65872e6d991_17",
  "file": "a9e28e47-2b12-4b48-a9b5-c65872e6d991_17",
  "tags": {
    "문학": 0.6
  },
  "metadata": {
    "source": "",
    "filename": "",
    "label": "",
    "chunk_index": 17
  },
  "tagging_time": "2025-05-07T22:24:46.663657",
  "auto_generated": true,
  "page_content": "다. 가정조차 지금 남어있는 것도 다 깨지고, 지금 남아 있는 것만큼 그런 식으로 자꾸 뚫으면 지금 남아있는 거마담도 내 육신까지 아직까지 건강도 있는 것마저도 전부다 후두려 팹니다. 이런 걸 당하고 싶다면 하십시오. 제를 만나기 전에 계 속 이렇게 해가꼬 계속 당하고 왔지 않습니까. 오다가 제를 만나서 공부하면서 지금 이기 멈 추고 있는 과정인데, 하고 싶으면 하십시오. 더 맛보겠다라고 하면 그건 누가 못 말립니다. 그렇겠죠. 어, 하니까 뚫는 방법은 한 가지 길 밖에 없습니다. 지금 이때까지 어려웠던 거. 이런 거는 놔두십시오. 이때까지 어려웠던 거는 내가 조금 견디면서 지금부터 내가 백일이라 도 석 달 열흘입니다. 이 백 일이 굉장히 소중한 겁니다. 왜 동안거 이 공부를 하느냐. 백 일 동안. 니 인생을 바꿀 수 있는 길이기 때문입니다. 왜 우리 민족이 백 일 기도를 그렇게 좋아하느냐. 백 일 정성이 면 대자연의 기운을 바꿔 놓는 게 인간입니다. 백 일 정성이면. 대자연의 기운도 니하고부터 주파수를 맞추어서 바꿔 버린다는 겁니다. 근데 백 일 정성을 하는데 정성의 방법을 몰라서 이때까지 백 일 기도들 많이 해 본 분들이 많죠. 헌데 관세음보살, 관세음보살, 관세음보살, 관세음보살 이카고 백 일 동안 앉아 있었고, 이러고 그냥 뭐, 뭐든지 안 생각 할라고 또 이렇 게 백 일 앉아 있었고, “하느님 아버지시여, 아버지시여 무조건 살려주십시오.” 이카고 백 일 동안 앉아 있었고. 이카다 보니 백 일 기도를 핸 사람이 없습니다. 매달리고, 쫄라 매, 매, 쪼, 쪼르고 부탁하고 이런 걸 백 일 동안 하고, 엉뚱한"
}