{
  "document_id": "ae168d33-cda8-475c-9ec1-c5eb2ee7be0f_1",
  "file": "ae168d33-cda8-475c-9ec1-c5eb2ee7be0f_1",
  "tags": {
    "문학": 0.6
  },
  "metadata": {
    "source": "",
    "filename": "",
    "label": "",
    "chunk_index": 1
  },
  "tagging_time": "2025-05-07T22:24:48.782025",
  "auto_generated": true,
  "page_content": "거죠 지금음 영적인 걸 다 이렇게 지금 다가 것을 내가 알고 있으니까 그 전에 있었던게 내가 고해를 많이 한게 주요 나를 버리시나이까 이때부터 이제 고민이 들어가는 거예요 그 안 앞에부터 고민이 들어왔거든 들어왔는데 이게 뭐냐 주여 나를 버리시나이까 이게 무슨 소리냐면 하느님이 나한테 영을 전부 다 주어서 앞에 다가올 것도 내가 말하는 것도 다 이루어 주셨는데 지금내가 이렇게 하고자 하는 걸 지금 안 이루어 주는 거예요 안 이루어 주니까 엄청나게 지금 그 그 스트레스를 받는 겁니다 말은 못하고 그 이게 아바 말 못하고 구이 눈물 난다는 거야요 이게 그 영을 받던 사람이 말이죠 갑자기 영을 못받으면 미쳐요 과거에 그런게 많았습니다 내가 영을 받다가 그저 기독교에도 영 받는 제자들이 많았어요 그런데 영을 받다가 있죠 언젠가 딱 끝나요 어 다른 제자도 그랬어 그런게 많았는데 애도 그게 온 거예요 영을 못 받으니까 그리고 내가 뜻을 이렇게 갖고 기도로 이렇게 원함을 해 주실 때가 있었는데 안 해 주거든 안 해 주니까 여기 스트레스가 엄청 받기 시작을 했어요 받기 시작을 해갖고 결국은 내가 하느님한테 무릎을 꿇으며 신이여 나를 버리시까 이때 피땀을 흘렸단다 피가 섞여 나와서 스트레스를 뛰기 받으면 말이에요이 그 저 이거 아주 잔 핏줄 있죠 이게 터져요 응 실핏줄 조금 이런 것들이 터져 갖고 이게 피부로 피가 흐릅니다 이게 땀에 이제 적 내려오는 이 이런 일들 예수가 고했던게 많아요 갖고 이런 것들이 때는 다가오고 어 나는 지금 이제 형로 가게끔 되가 있는 거 이런 걸 영적으로 다 본 거죠 그래서 모아놓고 최후의 만찬이"
}