{
  "document_id": "b4a67b33-4bf9-4f91-b416-8e5d48ed89ec_2",
  "file": "b4a67b33-4bf9-4f91-b416-8e5d48ed89ec_2",
  "tags": {},
  "metadata": {
    "source": "",
    "filename": "",
    "label": "",
    "chunk_index": 2
  },
  "tagging_time": "2025-05-07T22:24:41.412207",
  "auto_generated": true,
  "page_content": "니 생각이 들어가면 마음에너지는 가만히 있습니다. 작업을 안 해요. 그래서 니 생각으로 해내는 답은 원답을 찾기가 힘듭니다. 우리가 잘 나갈 때, 잘 우리가 살은 인생이니까. 연세에 계 신 분들은 이 말을 잘 방편으로 하면 이해가 될 것입니다. 우리가 한참 잘 나가고, 한참 뭐 일어 나고, 한참 내 뜻대로 잘 될 때. 이 때 우리가 생각을 했나요? 안 했습니다. 이 때는 생각을 하는 법이 없습니다. 내가 한참 승승장구하고 뭔가 잘될 때는 누가 내한테 그 소리를 딱 하면 그냥 결 정을 했지 요래볼까, 저래볼까 절대 생각을 안 했습니다. 이럴 때는 무엇이 나를 그렇게 신경을 안 쓰게끔 해도 되게끔 되가 있었느냐? 그 때는 모든 것이 마음이 결정을 하게끔 되가 있었습니 다. 그니께 듣자마자 바로 나옵니다. 들으면 나와. 그리고 그래서 인자 우리가 대화를 할 때, 남을 위할 때. 항상 대화를 할 때 니 각을 놓지 말고 그 사람 품성이 나오는대로 거둬줘라. 지금 그거 거둬주는 데는 손해가 없지 않냐. 그것을 거둬주는 것이 곧 덕행으로 이루어지는 것이다. 그니께 남편이 이야기를 하든, 부인이 이야기를 하든, 내 자식이 이야기 하든, 내 부모님이 이야기 할 때 는 “아, 예.” 하고는 그냥 받아만 주면 그 때는 내가 손해보는 게 없습니다. 난중에 결정할 때 손 해를 보냐, 안 보냐가 되는 것이지. 그거를 무심코 받아주라는 게, 무심이라는 말이 요 때 쓰는 말입니다. 무심을 다른 데다가 써버리면 안 되고. 수행할 때 무심으로 뭐 그게 아니고 상대가 있 을 때 무심이라는 단어를 쓰냐, 못 쓰냐가 되는 것입니다. 상대가 없이"
}