{
  "document_id": "c73fb173-a55f-4474-9f43-67b9af8cbddf_17",
  "file": "c73fb173-a55f-4474-9f43-67b9af8cbddf_17",
  "tags": {},
  "metadata": {
    "source": "",
    "filename": "",
    "label": "",
    "chunk_index": 17
  },
  "tagging_time": "2025-05-07T22:24:50.275990",
  "auto_generated": true,
  "page_content": "게 나무로 칭하니까 요렇게 해 주지만 인류 지판대 가면 요렇게 돼가 있는 겁니다. 이게 동쪽이고 이게 서쪽입니다. 그 요 렇게 해갖고 여게는 대장들이 앉아 있는 뎁니다. 피라밋이면 제일 높은데 갈수록 수가 줄어 들고 대표들이 앉아 있는 자리입니다. 여기가. 우리 저 3차원의 조직 구성이 그렇게 돼가 있고 3차원이 이렇게 피라밋으로 돼가 있는 겁니다. 그 제일 위에는 딱 한 사람만 올라가 앉아 있을 수 있게 돼가 있는 거라. 누가 제일 높은 사람이냐? 모든 중생들이 바르게 갈 길 을 인도해 주는 사람. [박수] 42분 14초 돈은 우리가 사업을 하니까 돈은 그 저 소비자들이 주죠. 소비자들이 주는데 돈 대신 뭐 준 다든지 돈을 다시 준다든지 이카면 소비자들이 싫어합니다. 고만큼 줬는데 그만큼 주버리면 싫어해요. 그러면 그 사람들을 위해서 사는 게 아니기 땜에 싫어하는 겁니다. 그 사람들은 우리가 작은 걸 줘도 돈을 더 보태가 우리한테 준 겁니다. 그걸 우리가 가져갔으면 돈으로 다시 돌리 달라는 소리는 아닌 겁니다. 우리한테 힘을 몰아주고 모든 것을 개발해가지고 서 양에서 전부다 개발해갖고 우리에게 못 줘가 환장을 합니다. 팔아물라 했던 어떻게 했던. 이 민족한테 못 줘가 환장을 하게 돼가 있습니다. 개발품을 갖고 모든지 일로 들어오게 돼 가 있습니다. 여게 들어오면 우리한테 쓰라고 갖고 오는 겁니다. 그 가지고 온 걸 우리가 쓸 줄을 지금 모르는 것입니다. 그거를 쓰고 너거는 그런 걸 만들어 열심히 해갖고 우리한 테 전부다 쓸 수 있는 이 기구를 만들어 주니까, 우리는 이것을 잘 써갖고 아주 지적인 걸 창출해갖"
}