{
  "document_id": "cd96fad8-7bf6-4e6f-a097-8e681edfc18d_21",
  "file": "cd96fad8-7bf6-4e6f-a097-8e681edfc18d_21",
  "tags": {
    "정신": 0.6
  },
  "metadata": {
    "source": "",
    "filename": "",
    "label": "",
    "chunk_index": 21
  },
  "tagging_time": "2025-05-07T22:24:49.584600",
  "auto_generated": true,
  "page_content": ". 그 마음 닦는다네. 그게 아 니예요. 마음은. 마음에너지는. 그게 나오는 게 지혜라는 거예요. 지혜. 마음에너지에서 바 른 답만 내주는 요거를 보고 지혜가 열렸다라고 하는 거라고. 지혜라는 게. 가마 놔두면 지 혜는 스스로 나오는 건데. 지혜는 뭐를 갖다가 어떻게 하는 게 아니예요. 바른 답만 탁탁 나와. 지혜라는 게. 하는 이 힘은 바른 답만 탁탁 나온다니까. 그러니까 천하무적이지. 저 적을 물리치는데 정확하게 바른 답이 톡 나오는 기라. 저 사람을 다스리는데 바른 답이 탁 나와. 다스리는데. 그런데 뭐 지혜를 얻으려고 이러고 36년을 앉아서 기다리는 놈이 없나. 천기를 받을라고 이카고 있는 게 없나. 니한테는 프리볼트로 천기가 다 연결되어 있어. 지 금. 마음의 에너지하고 연결되가 있기 때문에. 그래서 우리 민족은 마음으로 사는 민족이라 고. 마음으로 사는 민족. 그러니까 남을 위한다라는 건 니가 깨끗해야만 돼. 그래 백의민족 인거라. 백의민족이 옷 하얀 거 입었다고 백의민족이 아니고, 니 마음이 아주 깨끗한 걸 하 얀거로 표시를 한다 말이야. 아주 백옥같이 하얗고 맑다라는 소리거든. 그러니 백의민족이 라 말이야. 백의민족 그러면 옷 하얗게 그러면 전부 다 사막에 사는 사람들 누구야? 흰거 다 입고 다니니까 알라, 알라 이카는 사람들 전부 다 신선이네? 백의민족이네? 아니예요. 비유를 색깔을 든 것이지. 티 없이 맑은 걸 이야기하는 거거든. 마음이 티 없이 맑은 사람 들은 그래서 우리 저 위에서 신선님들이 살 때 그 모습이 있는 거라. 아주 지도력과 남을 깨우쳐주고 이끌어 주는 걸로 아주 존경을 받았던"
}