{
  "document_id": "d0640c74-3a88-4d23-a6ca-6bad825808dc_3",
  "file": "d0640c74-3a88-4d23-a6ca-6bad825808dc_3",
  "tags": {
    "문학": 0.6
  },
  "metadata": {
    "source": "",
    "filename": "",
    "label": "",
    "chunk_index": 3
  },
  "tagging_time": "2025-05-07T22:24:43.200988",
  "auto_generated": true,
  "page_content": "주고 있는 것이다 그러면 그 사람이 자기 일을 열심히 하겠끔 환경을 만들어 주는 거죠 그렇게 가면 어느 정도 이렇게 되면 뭐가 받칠 때는 내가 얼른 따주고 도와주고 어 렇게 가야지 심히 해야 될 심히 하도록 경을 들어주는 이것이 그 사람을 돕는 겁니다 내 말 잘 듣는 사람 도와야지 분명히 편에는 하게끔 돼 갖고 있습니다 아 말 안 듣는 사람은 그 사람은 신경을 안 써야 되는 거고 말 잘 듣는 사람은 이제부터 신경을 써서 인제를 만들어 내야 되는 거고 근데 그 사람을 바르게 대하는 법칙을 우리가 알아야 된다 가슴 속에는 너를 보고 있지만 가슴으로는 너를 보고 있다이 말이죠 내 육신으로는 너를 보는 책 하지 마라 조금씩 피해 주면서 네가 이런 일을 잘할 수 있도록 시간을 배려해 주라는 거죠 시간을 뺏지 마라 요런 것들 요런 환경들을 우리가 무가를지 모르는 것들을 지금 정리하는게 중요하지 당신들이 지금 지식이 무지해서 지금 사회를 처리 못하는게 아니에요이 중 어떻게 처리하는이 원리들을 모르고 있다는 거죠 내 감정이 너어 저저 내가 지식만 갖추다 보니까 감정이라는 걸 조종을 못 해요 어 그래서 이제 그는 감정 조종하는 것들도이 디자인의 원칙들을 우리가 바르게 이제 배우기 시작을 하면 지식은 다 갖춰 놨으니까이 지식의 힘을 어떻게 발휘할 수 있는 이런 것들을 알아야죠음 이해 돼요 [음악] 어 그 다시 섬세하게 하려고 하는 사람이 분류부터 어 그러면은 내가 말을 했지만 상태가 이해를 다 안 했을 것 같아요 그러면 이거 정리를 해 준다고 또 어 그러 하문 주입시켜 놓고 정리를 이렇게 해 주려고 한단 말이죠 하는데 정리를"
}