{
  "document_id": "f68a54e2-3c9e-48a2-ab37-968429839f86_11",
  "file": "f68a54e2-3c9e-48a2-ab37-968429839f86_11",
  "tags": {
    "문학": 0.6
  },
  "metadata": {
    "source": "",
    "filename": "",
    "label": "",
    "chunk_index": 11
  },
  "tagging_time": "2025-05-07T22:24:44.155271",
  "auto_generated": true,
  "page_content": "회를 줘가지고 다시 지금 인류의 공동체를 놓고 전부다 우리를 지원을 다시 줘가꼬 지금 뭔가를 시키려고 드는데, 아직 우리는 그 백신도 찾지 못 했고, 전부다 매여가꼬 정신적인, 사상적 인 전부다 이것들이 오만 세상에 있는 걸 다 들어왔는데, 지금 이게 뿌리에 다 들어왔어요. 나무가 물 내릴 때는 뿌리로 다 들어오는 거라. 세계적으로 인류에 지금 잘못된 논리는 전 부다 여기 다 들어와가 있어요. 이 나라에 다 들어와 있다고. 오만 사상이 다 들어와있어. 지금. 이거 논리 사상이거든. 왜 들어왔냐? 나무가 큰 무성하게 할 일을 많이 한 것 같아도 전부다 내릴 때는, 물을 내릴 때는 왜 내리냐? 잘못된 거를 전부다 다시 뿌리에서 정화를 해가지고 백신을 다시 정리를 해서 봄 되면 올려달라고 들어온 거라고. 그렇게 해가 꼬 모든 사상이 여기 다 들어오니까 지금 어떻게 됐냐? 그 안에 빠져가 놀고 쳐자빠졌어. 이걸 분석을 해가꼬 바로 잡아야 될 인류의 지도자 민족들이 여기 빠져가꼬 놀고 앉았는 거 라. 그래서 기업 윤리 사상도 다 들어와 있다고. 기업윤리도 잘못된 것이 다 들어온 것이 지, 잘된 것이 들어온 적이 없어요. 헌데 그것을 따라다니며 놀아. 이런 자가 이렇게 하니 까 여게서 빠져가 놀다가, 저런 자가 저걸 하나 가져오니까 저게 또 빠져가 놀다가, 저런 자가 저런 방법이 있다 하니 거기 빠져가 노네. 언제까지? 한 두 개 들어왔으면 벌써 탁 보 고 아니면은 수리를 해가꼬 우리꺼를 만들어냈어야 돼. 우리껄. 이 민족이 그걸 만들어내면 백신이 된다고. 이 백신이 되면 어떻게 되냐? 인류에 다시 돌려주면, 인류에 돌"
}