{
  "document_id": "f68a54e2-3c9e-48a2-ab37-968429839f86_6",
  "file": "f68a54e2-3c9e-48a2-ab37-968429839f86_6",
  "tags": {},
  "metadata": {
    "source": "",
    "filename": "",
    "label": "",
    "chunk_index": 6
  },
  "tagging_time": "2025-05-07T22:24:43.961860",
  "auto_generated": true,
  "page_content": "는 사람밖에 이 짓을 안 해요. 어떤 동물도 이 짓을 하는 동물은 없거든. 이 때 기운이 들어올 때 자지러 지는 거라 말이에요. 이게. 기운이 들어올 때. 육천육혈로 내가 들어가고 있는 중이거든. 이게 들어가야만, 가가 지고 육천육혈로 해서 그 자리에 전부다 이게 들어갈 때 가고 나야만 이게 인간환생 성공을 하는 거라 말이에요. 근데 이게 안 들어가면은 어떻게 하냐? 기형아에요. 70%에 멈춘다고. 실패작이거든. 이 30% 내 에너지가 들어가야만 인간이 돼. 인자는 동물이 아니라고. 인간이 야. 지금 게놈 뭐 프로젝트 풀고 뭐 어짜고 뭐, 뭐를 자꾸 해싸는데 천지도 모르는 소리 하 지마. 그 계산법이나 알아, 느그가? 동물 이거는 사람이 아니에요. 이거는 인간도 아니고. 이 안의 기운까지 포함을 해서 인간이라고. 그래서 애기도 인간인거야. 그러면 인간이면 동 물 육신을 70%를 쓰고 있기 때문에 이 근성이 동물육질대로 간다고. 이게. %수가. 그래서 동물처럼 사는 거에요. 동물로 살아. 거기에 끄달리고 산다고. 우리가. 끄달려가꼬 사는데 우리가 동물에서 인간으로. 동물적으로 사는 인간이 인자는 우리가 부모가 자식을 키울 때 는 사람으로 키우는 게 키우는 거라 말이에요. 무디기 키우는 게 키우는 게 아니고, 정신연 령을 바로 잡아서 내 에너지를 바로 쓸 수 있게끔. 인기가 바르게. 그렇게 해서 이 정신연 령을 바르게 키워가꼬 사람으로 성장을 시켜야만 완성품이 된다고. 이게. 그래서 3`7은 21. 21년 간을 부모님이 내 자식을 완성을 시켜내는 것이 부모가 할 도리라 말이에요. 이게. 헌 데 사람이 뭔지, 동물"
}