{
  "document_id": "intermediate/Youtube_0014강 봉사활동-2 아이가 자꾸 눈에 밟히고 선합니다.txt_chunk_0",
  "file": "Youtube_0014강 봉사활동-2 아이가 자꾸 눈에 밟히고 선합니다.txt_chunk_0",
  "tags": {},
  "metadata": {
    "filename": "Youtube_0014강 봉사활동-2 아이가 자꾸 눈에 밟히고 선합니다.txt",
    "format": ".txt",
    "file_path": "data/jungbub_teachings/intermediate/Youtube_0014강 봉사활동-2 아이가 자꾸 눈에 밟히고 선합니다.txt",
    "source": "천공 스승님 정법 가르침",
    "lecture_number": null,
    "title": null,
    "file_hash": "6b92b9e9c1a4227ba9cca1c65164b99c",
    "content_type": "lecture_qa",
    "category": "질의응답",
    "tags": [],
    "chunk_index": 0,
    "chunk_info": "청크 1 (문단 1)",
    "paragraph_indices": [
      0
    ],
    "total_chunks": 1,
    "chunk_id": "intermediate/Youtube_0014강 봉사활동-2 아이가 자꾸 눈에 밟히고 선합니다.txt_chunk_0",
    "source_file": "intermediate/Youtube_0014강 봉사활동-2 아이가 자꾸 눈에 밟히고 선합니다.txt"
  },
  "tagging_time": "2025-05-05T00:21:45.822485",
  "auto_generated": true
}